setup.cfg
setup.py
zicbee_gst/__init__.py
zicbee_gst/core.py
zicbee_gst.egg-info/PKG-INFO
zicbee_gst.egg-info/SOURCES.txt
zicbee_gst.egg-info/dependency_links.txt
zicbee_gst.egg-info/entry_points.txt
zicbee_gst.egg-info/top_level.txt