Metadata-Version: 1.0
Name: zicbee-gst
Version: 0.6.1
Summary: Gstreamer backend for zicbee project
Home-page: http://zicbee.gnux.info/
Author: Fabien Devaux
Author-email: fdev31@gmail.com
License: BSD
Download-URL: http://zicbee.gnux.info/hg/zicbee-gst/archive/0.6.1.tar.bz2
Keywords: database music tags metadata management
Platform: UNKNOWN
Classifier: Development Status :: 4 - Beta
Classifier: Intended Audience :: Developers
Classifier: Operating System :: OS Independent
Classifier: Operating System :: Microsoft :: Windows
Classifier: Operating System :: POSIX
Classifier: Programming Language :: Python
Classifier: Environment :: Console
Classifier: Environment :: No Input/Output (Daemon)
Classifier: Environment :: X11 Applications
Classifier: Natural Language :: English
Classifier: Topic :: Internet :: WWW/HTTP :: WSGI :: Application
Classifier: Topic :: Internet :: WWW/HTTP :: Indexing/Search
Classifier: Topic :: Internet :: WWW/HTTP :: Dynamic Content
Classifier: Topic :: Software Development
Classifier: Topic :: Software Development :: Libraries :: Python Modules
Classifier: Topic :: Multimedia :: Sound/Audio :: Players
Classifier: Topic :: Multimedia :: Sound/Audio :: Players :: MP3
Classifier: Topic :: Text Processing :: Markup
Classifier: Topic :: Utilities
